<?xml version="1.0" encoding="utf-8"?>
<entries>
<text id="72200100">###2（无译文）怎么了？不死人旅行者？
我可没时间管你了。#3</text>
<text id="72200110">###2（无译文）嗯，跨越时空之壁前往过去…#3</text>
<text id="72200120">###2（无译文）…#3</text>
<text id="72200130">###2（无译文）……#3</text>
<text id="72200140">###2（无译文）…啊，走神了。
这个给你，快点出去吧。#3</text>
<text id="72200200">###2（无译文）…………#3</text>
<text id="72200210">###2（无译文）连接时空需要的“时间之摆”要把…#3</text>
<text id="72200300">###2（无译文）…………#3</text>
<text id="72200310">###2（无译文）“龙之宝玉”、“时间水滴”的…#3</text>
<text id="72200400">###2（无译文）照现在这样时间之摆依然动不起来。#3</text>
<text id="72200410">###2（无译文）但在恶魔横行的这个世界…#3</text>
<text id="72200420">###2（无译文）…啊，集中注意力！#3</text>
<text id="72200430">###2（无译文）…怎么了？你想借助我的智慧？
我不认为一个不学无术的人能理解我的话…喂，听好了。#3</text>
<text id="72200440">###2（无译文）我是贝尔德里克，
这个国家里头脑最聪明的人。#3</text>
<text id="72200450">###2（无译文）因为，我知道“时间穿越之摆”的真相，#3</text>
<text id="72200460">###2（无译文）…哼。反正是你做不到的事。
你是这么想的吧？凡人都是这么想的。#3</text>
<text id="72200470">###2（无译文）但是，我的字典里没有错误。那些把我当傻瓜的家伙，
看到钟摆的时候，也是大吃一惊。#3</text>
<text id="72200480">###2（无译文）如果用钟摆回到过去，拜托现在下落不明的陛下，
就有可能夺回王城。#3</text>
<text id="72200490">###2（无译文）怎么样，不觉得很了不起吗！？#3</text>
<text id="72200600">###2（无译文）什么，还说不信我的话？
所以你们这些个凡人…#3</text>
<text id="72200610">###2（无译文）还有疑问的话就去王冠看看吧，
我研究“时间之摆”的房间就在那。#3</text>
<text id="72200620">###2（无译文）就算是傻瓜亲眼所见，也该明白真相了吧。#3</text>
<text id="72200700">###2（无译文）你知道自古生存的龙族胎中，
藏着稀有宝珠的传说吗？#3</text>
<text id="72200710">###2（无译文）看来和“古老之龙”产生的灵魂有关系…#3</text>
<text id="72200720">###2（无译文）所以我认为，只要去寻找渴求灵魂的恶魔，
就能找到宝珠。#3</text>
<text id="72200800">###2（无译文）某个古老村子里有个有趣的传说。#3</text>
<text id="72200810">###2（无译文）在地下深处挖掘的矿工，
在洞穴深处的尽头发现了翻腾不息的水。#3</text>
<text id="72200820">###2（无译文）然后他将一口水，含在口中，
下一刻，矿工就回到了地面上。#3</text>
<text id="72200830">###2（无译文）…知道这个故事后，我恍然大悟，
这不正是“时空之洞”吗…#3</text>
<text id="72200840">###2（无译文）恶魔们毁灭了那个村子，
那个洞穴在哪里，已经无从得知了。#3</text>
<text id="72200850">###2（无译文）但是，涌泉现在应该还在地下沉眠着。#3</text>
<text id="72200900">###2（无译文）如果把“宝珠”和“水滴”做成钟摆，
将宇宙之理开一个洞，就可以穿越时间…#3</text>
<text id="72200910">###2（无译文）再给一点时间，我的研究就能成功了…本该是这样的。#3</text>
<text id="72200920">###2（无译文）但就在钟摆要完成前王宫陷落了，
现在没办法再接近了。#3</text>
<text id="72200930">###2（无译文）没骨气的军师们，要是能再有点智慧，
也就不会这样结束了…#3</text>
<text id="72201000">###2（无译文）那是“宝珠”！？也就是说…
…果然，我的想法是正确的！！#3</text>
<text id="72201010">###2（无译文）哈哈哈。果然是正确的，
我的头脑是世界第一。#3</text>
<text id="72201100">###2（无译文）那清澈的液体…是“时间水滴”！？
果然，我的想法是正确的！！#3</text>
<text id="72201110">###2（无译文）哈哈哈。果然是正确的，
我的头脑是世界第一。#3</text>
<text id="72201200">###2（无译文）像你这样的凡人，竟能集齐两件秘宝…
无知无畏竟然也能派上用场吗？#3</text>
<text id="72201210">###2（无译文）但是，只是这样还不行。
当两件秘宝被做成钟摆时，初始之门才会打开。#3</text>
<text id="72201220">###2（无译文）“时间之摆”所沉眠的皇宫，现在已经是游魂的巢穴。
怎么想也不觉得你能平安抵达。#3</text>
<text id="72201300">###2（无译文）什么！？“时间之摆”动起来了！？
除了我之外的人也能做到…#3</text>
<text id="72201310">###2（无译文）但是，我的理论是正确的…
只要集齐秘宝，凡人也不是不可能的…#3</text>
<text id="72201320">###2（无译文）既然如此，
我要亲眼看看，去确认下研究的成果。#3</text>
<text id="72201400">###2（无译文）既然如此，
我要亲眼看看，去确认下研究的成果。#3</text>
<text id="72209000">###2（无译文）唔…！#3</text>
<text id="72209010">###2（无译文）你，想干什么！？#3</text>
<text id="72209020">###2（无译文）还不住手！#3</text>
<text id="72209030">###2（无译文）愚蠢！#3</text>
<text id="72209100">###2（无译文）我的研究多么有用，
你好像没办法理解啊！#3</text>
<text id="72209200">###2（无译文）又来了！
不能再容许愚蠢的行为了！#3</text>
<text id="72209300">###2（无译文）笨蛋，这么快就暴跳如雷…#3</text>
<text id="72209310">###2（无译文）可恶…我不想战斗…#3</text>
<text id="72209320">###2（无译文）还不能死。还不能死啊！#3</text>
<text id="72209400">###2（无译文）我的…研究还…没完成…#3</text>
<text id="72209500">###2（无译文）和无聊的人打交道，已经受够了。#3</text>
</entries>