<?xml version="1.0" encoding="utf-8"?>
<entries>
<text id="10000">カタリナヘルム</text>
<text id="11000">カタリナアーマー</text>
<text id="12000">カタリナガントレット</text>
<text id="13000">カタリナレギンス</text>
<text id="20000">聖騎士の兜</text>
<text id="21000">聖騎士の鎧</text>
<text id="22000">聖騎士の手甲</text>
<text id="23000">聖騎士の足甲</text>
<text id="40000">闇の仮面</text>
<text id="41000">闇の鎧</text>
<text id="42000">闇の手甲</text>
<text id="43000">闇の足甲</text>
<text id="50000">山賊の頭巾</text>
<text id="51000">山賊の鎧</text>
<text id="52000">山賊の篭手</text>
<text id="53000">山賊のズボン</text>
<text id="60000">影の覆面</text>
<text id="61000">影の上衣</text>
<text id="62000">影の手甲</text>
<text id="63000">影の足甲</text>
<text id="70000">黒鉄の兜</text>
<text id="71000">黒鉄の鎧</text>
<text id="72000">黒鉄の手甲</text>
<text id="73000">黒鉄の足甲</text>
<text id="80000">スモウの兜</text>
<text id="81000">スモウの鎧</text>
<text id="82000">スモウの手甲</text>
<text id="83000">スモウの足甲</text>
<text id="90000">伝道者の六目兜</text>
<text id="91000">伝道者の聖衣</text>
<text id="92000">伝道者の篭手</text>
<text id="93000">伝道者の腰巻き</text>
<text id="100000">寵愛の兜</text>
<text id="101000">寵愛の抱かれ鎧</text>
<text id="102000">寵愛の手甲</text>
<text id="103000">寵愛の足甲</text>
<text id="110000">知恵者の兜</text>
<text id="111000">名誉者の鎧</text>
<text id="112000">獲得者の篭手</text>
<text id="113000">探索者の長靴</text>
<text id="120000">石の兜</text>
<text id="121000">石の鎧</text>
<text id="122000">石の手甲</text>
<text id="123000">石の足甲</text>
<text id="130000">結晶付きの兜</text>
<text id="131000">結晶付きの鎧</text>
<text id="132000">結晶付きの手甲</text>
<text id="133000">結晶付きの足甲</text>
<text id="140000">封印者の仮面</text>
<text id="141000">紅のローブ</text>
<text id="142000">紅のグローブ</text>
<text id="143000">紅の腰巻き</text>
<text id="150000">ベルカの仮面</text>
<text id="151000">黒の聖職衣</text>
<text id="152000">黒のマンシェット</text>
<text id="153000">黒のタイツ</text>
<text id="160000">鉄の兜</text>
<text id="161000">太陽印の鎧</text>
<text id="162000">鉄の腕輪</text>
<text id="163000">鉄の足甲</text>
<text id="170000">チェインヘルム</text>
<text id="171000">チェインアーマー</text>
<text id="172000">レザーガントレット</text>
<text id="173000">チェインレギンス</text>
<text id="180000">聖職の兜</text>
<text id="181000">聖職の鎧</text>
<text id="182000">聖職の手甲</text>
<text id="183000">聖職の足甲</text>
<text id="190000">太陽虫</text>
<text id="200000">トゲの兜</text>
<text id="201000">トゲの鎧</text>
<text id="202000">トゲの手甲</text>
<text id="203000">トゲの足甲</text>
<text id="210000">アイアンヘルム</text>
<text id="211000">ハードレザーアーマー</text>
<text id="212000">ハードレザーガントレット</text>
<text id="213000">ハードレザーブーツ</text>
<text id="220000">魔術師の帽子</text>
<text id="221000">魔術師のコート</text>
<text id="222000">魔術師のガントレット</text>
<text id="223000">魔術師のブーツ</text>
<text id="230000">ボロ布のフード</text>
<text id="231000">ボロ布のローブ</text>
<text id="232000">ボロ布のマンシェット</text>
<text id="233000">厚手のブーツ</text>
<text id="240000">ファリスの帽子</text>
<text id="241000">レザーアーマー</text>
<text id="242000">レザーグローブ</text>
<text id="243000">レザーブーツ</text>
<text id="250000">絵画守りの頭巾</text>
<text id="251000">絵画守りの長衣</text>
<text id="252000">絵画守りの長手袋</text>
<text id="253000">絵画守りの腰巻き</text>
<text id="270000">オーンスタインの兜</text>
<text id="271000">オーンスタインの鎧</text>
<text id="272000">オーンスタインの手甲</text>
<text id="273000">オーンスタインの足甲</text>
<text id="280000">東国の兜</text>
<text id="281000">東国の鎧</text>
<text id="282000">東国の手甲</text>
<text id="283000">東国の足甲</text>
<text id="290000">黄衣の冠</text>
<text id="291000">黄の上衣</text>
<text id="292000">黄衣の長手袋</text>
<text id="293000">黄衣の腰巻き</text>
<text id="300000">盗人マスク</text>
<text id="301000">黒革の鎧</text>
<text id="302000">黒革の手袋</text>
<text id="303000">黒革のブーツ</text>
<text id="310000">司祭の帽子</text>
<text id="311000">聖職の上衣</text>
<text id="312000">旅の手袋</text>
<text id="313000">聖職のズボン</text>
<text id="320000">黒騎士の兜</text>
<text id="321000">黒騎士の鎧</text>
<text id="322000">黒騎士の手甲</text>
<text id="323000">黒騎士の足甲</text>
<text id="330000">宵闇の頭冠</text>
<text id="331000">古めかしいドレス</text>
<text id="332000">古めかしいロンググローブ</text>
<text id="333000">古めかしいスカート</text>
<text id="340000">魔女のとんがり帽子</text>
<text id="341000">魔女のコート</text>
<text id="342000">魔女のグローブ</text>
<text id="343000">魔女のスカート</text>
<text id="350000">上級騎士の兜</text>
<text id="351000">上級騎士の鎧</text>
<text id="352000">上級騎士の手甲</text>
<text id="353000">上級騎士の足甲</text>
<text id="360000">放浪のフード</text>
<text id="361000">放浪のコート</text>
<text id="362000">放浪のマンシェット</text>
<text id="363000">放浪のブーツ</text>
<text id="380000">ビッグハット</text>
<text id="381000">賢者のローブ</text>
<text id="382000">旅の長手袋</text>
<text id="383000">旅の靴</text>
<text id="390000">騎士の兜</text>
<text id="391000">騎士の鎧</text>
<text id="392000">騎士の手甲</text>
<text id="393000">騎士の足甲</text>
<text id="400000">うす汚れたフード</text>
<text id="401000">うす汚れた上衣</text>
<text id="402000">うす汚れた手袋</text>
<text id="403000">血濡れたスカート</text>
<text id="410000">聖女のフード</text>
<text id="411000">聖女の上衣</text>
<text id="412000">聖女の手袋</text>
<text id="413000">聖女のスカート</text>
<text id="420000">銀騎士の兜</text>
<text id="421000">銀騎士の鎧</text>
<text id="422000">銀騎士の手甲</text>
<text id="423000">銀騎士の足甲</text>
<text id="440000">ハベルの兜</text>
<text id="441000">ハベルの鎧</text>
<text id="442000">ハベルの手甲</text>
<text id="443000">ハベルの足甲</text>
<text id="450000">真鍮の兜</text>
<text id="451000">真鍮の鎧</text>
<text id="452000">真鍮の手甲</text>
<text id="453000">真鍮の足甲</text>
<text id="460000">黒金糸のフード</text>
<text id="461000">黒金糸のローブ</text>
<text id="462000">黒金糸のロンググローブ</text>
<text id="463000">黒金糸のスカート</text>
<text id="470000">ゴーレムヘルム</text>
<text id="471000">ゴーレムアーマー</text>
<text id="472000">ゴーレムガントレット</text>
<text id="473000">ゴーレムレギンス</text>
<text id="480000">亡者兵士の兜</text>
<text id="481000">亡者兵士の鎧</text>
<text id="483000">亡者兵士の腰巻き</text>
<text id="490000">鋼鉄の兜</text>
<text id="491000">鋼鉄の鎧</text>
<text id="492000">鋼鉄の手甲</text>
<text id="493000">鋼鉄の足甲</text>
<text id="500000">亡者盗賊のフード</text>
<text id="501000">亡者盗賊の革鎧</text>
<text id="503000">亡者盗賊のタイツ</text>
<text id="510000">バルデルの兜</text>
<text id="511000">バルデルの鎧</text>
<text id="512000">バルデルの手甲</text>
<text id="513000">バルデルの足甲</text>
<text id="520000">亡者戦士の兜</text>
<text id="521000">亡者戦士の鎧</text>
<text id="523000">亡者戦士の腰巻き</text>
<text id="530000">巨人の兜</text>
<text id="531000">巨人の鎧</text>
<text id="532000">巨人の手甲</text>
<text id="533000">巨人の足甲</text>
<text id="540000">陰の太陽の王冠</text>
<text id="541000">月光の長衣</text>
<text id="542000">月光の長手袋</text>
<text id="543000">月光の腰巻き</text>
<text id="550000">大王の王冠</text>
<text id="551000">大王の長衣</text>
<text id="552000">大王の腕輪</text>
<text id="553000">大王の脚輪</text>
<text id="560000">ずた袋</text>
<text id="570000">貪欲者の烙印</text>
<text id="580000">王族の兜</text>
<text id="590000">父の仮面</text>
<text id="600000">母の仮面</text>
<text id="610000">子の仮面</text>
<text id="620000">牙猪の兜</text>
<text id="630000">ガーゴイルの兜</text>
<text id="640000">魔術師の黒帽子</text>
<text id="641000">魔術師の黒コート</text>
<text id="642000">魔術師の黒ガントレット</text>
<text id="643000">魔術師の黒ブーツ</text>
<text id="660000">アルトリウスの兜</text>
<text id="661000">アルトリウスの鎧</text>
<text id="662000">アルトリウスの手甲</text>
<text id="663000">アルトリウスの足甲</text>
<text id="670000">白磁の仮面</text>
<text id="671000">王刃の長衣</text>
<text id="672000">王刃の長手袋</text>
<text id="673000">王刃の腰巻き</text>
<text id="680000">ゴーの兜</text>
<text id="681000">ゴーの鎧</text>
<text id="682000">ゴーの手甲</text>
<text id="683000">ゴーの足甲</text>
<text id="690000">守護者の兜</text>
<text id="691000">守護者の鎧</text>
<text id="692000">守護者の手甲</text>
<text id="693000">守護者の足甲</text>
<text id="700000">微笑みロングハット</text>
<text id="701000">チェスターのロングコート</text>
<text id="702000">チェスターのグローブ</text>
<text id="703000">チェスターのズボン</text>
<text id="710000">肥大した頭部</text>
<text id="720000">肥大した魔術師の頭部</text>
<text id="370000">##魔術鍛冶の帽子</text>
<text id="371000">##魔術鍛冶のコート</text>
<text id="372000">##魔術鍛冶のガントレット</text>
<text id="373000">##魔術鍛冶のブーツ</text>
<text id="650000">##上位聖職の兜</text>
<text id="651000">##上位聖職の鎧</text>
<text id="652000">##上位聖職の手甲</text>
<text id="653000">##上位聖職の足甲</text>
<text id="1000000">##竜の頭</text>
<text id="1001000">##竜の体</text>
<text id="1002000">##竜の腕</text>
<text id="1003000">##竜の脚</text>
<text id="1010000">##たまご</text>
</entries>