<?xml version="1.0" encoding="utf-8"?>
<entries>
<text>#0第1次攀谈</text>
<text id="29000000">唷，新来的。</text>
<text id="29000004">我是亚斯特拉的安德烈。</text>
<text id="29000005">我是个铁匠，要冶炼的话可以来找我。</text>
<text>#0第2次攀谈</text>
<text id="29000100">唷，是你啊。</text>
<text id="29000101">你看来没事，真是太好了。</text>
<text id="29000102">有什么要冶炼的吗？</text>
<text>#0互动列表-第1次选择「交谈」</text>
<text id="29000200">武器和防具都是很坚固耐用的没错，</text>
<text id="29000201">但是一直使用而不维修的话，是肯定会坏的，</text>
<text id="29000202">所以当武器防具的耐用度降低时，就要勤加修理。</text>
<text id="29000203">你可以拿给我这样的铁匠修，
若有工具的话，你也可以自己修。</text>
<text id="29000204">武器防具是你的战友，绝对不会背叛你的，</text>
<text id="29000205">请好好地对待吧。</text>
<text>#0互动列表-第2次选择「交谈」</text>
<text id="29000300">武器的冶炼方式大致分为两种，
强化和进化。</text>
<text id="29000301">强化很简单，
就是不改变武器性质，只强化武器。</text>
<text id="29000302">你可以拿给我这样的铁匠冶炼，
有打铁箱时也可以自己做。</text>
<text id="29000303">但是进化就不同了，这会改变武器性质，是高等的冶炼技术。</text>
<text id="29000304">所以进化不能用打铁箱自己搞，
要交给我这种专业的来处理啦。</text>
<text id="29000305">不过强化会有到极限的时候，
到那时再考虑要不要进化吧。</text>
<text id="29000306">我想你也应该知道了，
这片土地没有人是正常的。</text>
<text id="29000307">武器一直不去冶炼的话，
终究是会没有办法应付的。</text>
<text id="29000308">哈哈哈</text>
<text>#0互动列表-第3次选择「交谈」</text>
<text id="29000400">嗯，防具的冶炼方式和武器几乎是相同的。</text>
<text id="29000402">因为防具就只有强化，比武器更加简单啊。</text>
<text id="29000403">武器和防具，要哪个先冶炼就看你自己啦。</text>
<text id="29000404">我可不愿意看到你变成游魂啊，</text>
<text id="29000405">请深思熟虑后再做决定吧。</text>
<text id="29000406">哈哈哈</text>
<text>#0在营火休息后，互动列表-第1次选择「交谈」</text>
<text id="29000500">这里是古老教堂，</text>
<text id="29000501">你之前经过的不死教堂，
是舍弃这里后才建的。</text>
<text id="29000502">不过那不是重点，我要说的是这里通往两个古老禁区，
赛恩古城及黑森林庭院。</text>
<text id="29000503">赛恩古城及黑森林庭院，都不是什么正常人会去的地方</text>
<text id="29000504">……但我也没看过什么正常的不死人就是了。</text>
<text id="29000505">哈哈哈</text>
<text>#0在营火休息后，互动列表-第2次选择「交谈」</text>
<text id="29000600">赛恩古城是古代神所建造，用来考验人的，</text>
<text id="29000601">传说从那往前走，有神的城堡──
伟大的亚诺尔隆德。</text>
<text id="29000602">话说回来，
大部分的不死人是连进到古城都办不到的，</text>
<text id="29000603">就像那个洋葱骑士一样。</text>
<text id="29000604">哈哈哈</text>
<text>#0在营火休息后，互动列表-第3次选择「交谈」</text>
<text id="29002700">我也不太清楚黑森林庭院的事。</text>
<text id="29002701">不过听说以前那边
有一位会冶炼的圣职。</text>
<text id="29002702">在地下墓地一带遇到瓶颈的那些家伙，
因为想要神圣武器，所以常常到这里来。</text>
<text>#0开启小隆德水门后，互动列表-选择「交谈」</text>
<text id="29002800">啊，对了，还有一件关于黑森林庭院的传闻。</text>
<text id="29002801">据说那边有“漫步深渊”的骑士，亚尔特留斯的坟墓。</text>
<text id="29002802">不过，告诉我传闻的那些到森林去的人，
一个都没回来……</text>
<text>#0持有大块余烬时攀谈</text>
<text id="29001200">喂，你手上有不错的余烬啊。</text>
<text id="29001201">把余烬交给我吧，怎样？</text>
<text id="29001202">给我的话，我就可以做出更好的武器喔。</text>
<text>#0您要将大块余烬交给对方吗？选择「否」</text>
<text id="29001300">好吧……真可惜……</text>
<text>#0您要将大块余烬交给对方吗？选择「是」</text>
<text id="29001400">太好了，就交给我吧。</text>
<text id="29001401">看我展现铁匠的实力吧。</text>
<text>#0持有特大块余烬时攀谈</text>
<text id="29001450">喂，你手上有很棒的余烬啊！</text>
<text id="29001451">我打铁这行做这么久了，没看过这么棒的！</text>
<text id="29001452">把余烬交给我吧，拜托啦？</text>
<text id="29001453">我好歹是个打铁的，
看到这么棒的东西，实在是忍不住啊。</text>
<text>#0您要将特大块余烬交给对方吗？选择「否」</text>
<text id="29001460">好吧……那真可惜……</text>
<text id="29001461">但是……</text>
<text id="29001462">啊，没，没关系……</text>
<text id="29001463">没关系……</text>
<text>#0您要将特大块余烬交给对方吗？选择「是」</text>
<text id="29001470">是吗！要给我吗！</text>
<text id="29001471">太好了，就交给我吧！</text>
<text id="29001472">我办事你放心，就交给我亚斯特拉的安德烈吧！</text>
<text>#0持有圣职余烬时攀谈</text>
<text id="29001500">喂，你有个很少见的余烬啊！</text>
<text id="29001501">我有看过一次……
这是圣职冶炼用的余烬啊。</text>
<text id="29001502">把余烬交给我吧，怎样？</text>
<text id="29001503">搞不好可以制作出神圣武器啊。</text>
<text>#0您要将圣职余烬交给对方吗？选择「否」</text>
<text id="29001600">好吧……那真遗憾……</text>
<text>#0您要将圣职余烬交给对方吗？选择「是」</text>
<text id="29001700">喔，要给我吗！</text>
<text id="29001701">正确的判断！就交给我吧！</text>
<text>#0持有大块圣职余烬时攀谈</text>
<text id="29001800">喂，你手上有很棒的余烬啊……</text>
<text id="29001801">连我都只听过，还没看过……</text>
<text id="29001802">这余烬，一定是圣职在秘密仪式用的……</text>
<text id="29001803">把余烬交给我吧，拜托啦？</text>
<text id="29001804">这样一来，我就可以实现制作神圣武器的心愿了。</text>
<text>#0您要将大块圣职余烬交给对方吗？选择「否」</text>
<text id="29001900">好吧……那真可惜……</text>
<text id="29001901">没关系，那本来就是你的……</text>
<text>#0您要将大块圣职余烬交给对方吗？选择「是」</text>
<text id="29002000">喔，要给我吗！太感谢了！</text>
<text id="29002001">我亚斯特拉的安德烈，绝对不会让你失望的！</text>
<text>#0持有黑暗余烬时攀谈</text>
<text id="29002100">嗯？你拥有的那个余烬……</text>
<text id="29002101">黑色的余烬，从来没有听过耶……</text>
<text id="29002102">嗯……</text>
<text id="29002103">把余烬交给我看看吧，拜托啦？</text>
<text id="29002104">不知道为什么，就有股诱人的感觉……</text>
<text>#0您要将黑暗余烬交给对方吗？选择「否」</text>
<text id="29002200">好吧……没关系。</text>
<text id="29002201">真可惜，我就当做没看过吧。</text>
<text>#0您要将黑暗余烬交给对方吗？选择「是」</text>
<text id="29002300">是吗，要给我吗！</text>
<text id="29002301">好棒的余烬啊。
实在是很吸引人……</text>
<text id="29002302">我有好预感……</text>
<text>#0持有其他余烬时攀谈</text>
<text id="29002400">喂，你手上有个奇怪的余烬耶。</text>
<text id="29002401">……我知道你想说什么，
但是这已超出我的能力范围，</text>
<text id="29002402">抱歉，请你找别人吧。</text>
<text id="29002403">不过，我想应该没有人会……</text>
<text>#0完成交易后，互动列表-选择「离去」</text>
<text id="29002600">……可不要死了喔。</text>
<text id="29002601">我可不想看到你变成游魂的样子。</text>
<text>#0未完成交易，互动列表-选择「离去」</text>
<text id="29002500">……再会啦。</text>
<text id="29002501">可不要太逞强啊……</text>
<text>#0走开中断对话</text>
<text id="29000700">喂，你要去哪里啊？</text>
<text>#0走开中断对话后，返回攀谈</text>
<text id="29000800">你刚才是突然怎么了，真是的。</text>
<text id="29000801">我还以为你变成游魂了呢。</text>
<text id="29000802">哈哈哈</text>
<text>#0第1次受到攻击时</text>
<text id="29000900">好痛！</text>
<text>#0第2次受到攻击时</text>
<text id="29000950">会痛的耶！</text>
<text>#0攻击导致敌对时</text>
<text id="29001000">好样的，你玩真的！</text>
<text id="29001001">不要给我开玩笑！</text>
<text id="29001002">看我宰了你！臭游魂！</text>
<text>#0被击杀时</text>
<text id="29001100">混蛋……</text>
<text id="29000001">##你在烦恼没办法进入不死教堂吗？</text>
<text id="29000002">##拿这把钥匙去用吧。</text>
<text id="29000003">##反正我已经用不到了。</text>
<text id="29000401">##强化不难，有打铁箱就可以自己强化，
进化的话就要交给我这种专业的。</text>
</entries>