<?xml version="1.0" encoding="utf-8"?>
<entries>
<text id="37000000">唷！你来得正好，已经好久没见到新来的啦。</text>
<text id="37000001">我想你八成是为了那些事而来的吧？
不死人的使命之类的……大家都一样。</text>
<text id="37000002">遭受诅咒的时候一切就都完啦，
一直待在不死院才是比较明智的抉择……你苦啦。</text>
<text id="37000003">不过也无所谓啦，反正我闲着也是闲着，就教教你吧。</text>
<text id="37000004">在不死人的使命中提到的苏醒之钟总共有两口，</text>
<text id="37000005">其中一口就放在此地上方，不死教堂的钟楼，
而另一口则是放在此地下方深处，病村底下的古代遗迹中。</text>
<text id="37000006">据说只要敲响这两口钟，就会发生某些事，
不过……谁知道会怎样呢？</text>
<text id="37000007">至少就我而言，是从没听说过后来怎样啦……
反正也没差。</text>
<text id="37000008">快上路吧，
你来到这个受诅咒的不死人之地，不就是为这件事吗？</text>
<text id="37000009">……呵呵呵呵呵</text>
<text id="37000100">嗯？怎么了？你还有什么问题吗？</text>
<text id="37000101">虽说我不大喜欢太爱问东问西的人……算了，无所谓。</text>
<text id="37000102">我就再稍微教你一些事吧。</text>
<text id="37000103">虽然说其中一口钟确实放在此地上方的不死教堂，
但现在升降梯已经不动了。</text>
<text id="37000104">所以说，你只能沿着旁边的山崖往上爬，
从水路进入不死镇。</text>
<text id="37000105">另一口钟，就从那座不死镇往下走就可以了。</text>
<text id="37000106">……但话说回来，不死镇下去可是座聚集了许多病患的病村。</text>
<text id="37000107">如果是我的话，可是会希望离那地方远远的呢。</text>
<text id="37000108">哇哈哈哈哈哈</text>
<text id="37000200">喂喂，你还有问题要问呀？</text>
<text id="37000201">如果太爱问东问西的话，可是会惹人厌的喔。</text>
<text id="37000300">怎么了？觉得害怕了吗？</text>
<text id="37000301">既然如此，那就和我一样，一直在这边坐下去就好啦。</text>
<text id="37000302">浑浑噩噩过日子，直到自己成为游魂，是最轻松的啦。</text>
<text id="37000303">……呵呵呵呵呵</text>
<text id="37000400">喔，是你呀。真令我意外，没想到你还没事啊。</text>
<text id="37000401">……说到这边，我刚刚听到了钟声……难不成那是你敲响的？</text>
<text id="37000402">如果真是如此，那你还真有热忱啊。叫我自叹弗如哩。</text>
<text id="37000403">干脆就打铁趁热，努力去搞定另一个烫手山芋吧？</text>
<text id="37000404">干脆就打铁趁热，努力地去搞定另一边的吧？</text>
<text id="37000405">……呵呵呵呵呵</text>
<text id="37000500">说到这边，刚刚我才看到了一群很高贵的圣职，
从墓地进入地下墓地了呢。</text>
<text id="37000501">听起来，在那票家伙的传说中，
似乎有说到让不死营火烧得更旺──“注火”这档事呢。</text>
<text id="37000502">那票家伙全都到地下墓地去了。
是因为和尚知道埋葬很费事，才特地跑去那里的吗？</text>
<text id="37000503">哇哈哈哈哈哈</text>
<text id="37000600">你已经去过这下面的小隆德遗迹了吗？</text>
<text id="37000601">只要从这边的楼梯往下走，再搭乘升降梯，就可以立刻抵达了。</text>
<text id="37000602">如果还没去过的话，最好去一下看看。</text>
<text id="37000603">那是座古老的不死人遗迹，说不定藏着什么关于使命的提示呢。</text>
<text id="37000604">举例来说，像是亡灵的欢迎之类的……</text>
<text id="37000605">哼哼哼哼</text>
<text id="37000700">说到这边，不知道那家伙现在过得如何呢。</text>
<text id="37000701">之前我曾遇到个用魔法的，
说他正在找“大帽子”什么的……</text>
<text id="37000702">自从他动身前往不死镇之后，就再也没回来过了。</text>
<text id="37000703">不觉得很蠢吗？如果是那个“大帽子”就算了，
像他那种货色根本一点用都没有……</text>
<text id="37000704">看来他一定已经在哪边成为游魂了……</text>
<text id="37000800">说到这边，不知道那家伙现在过得如何呢。</text>
<text id="37000801">之前我曾遇到个肮脏咒术师，
老是在说咒术始祖之类一点道理都没有的事……</text>
<text id="37000802">自从他动身前往病村之后，就再也没回来过了。</text>
<text id="37000803">真是个怪人对吧？什么地方不好去，偏偏要去那座病村。</text>
<text id="37000804">看来他一定已经在哪边成为游魂了……</text>
<text id="37000900">什么？那圣职竟然平安无事？</text>
<text id="37000901">没想到神明竟然那么没有眼光啊……</text>
<text id="37000902">啧……</text>
<text id="37001000">什么？那个用魔法的竟然平安无事……</text>
<text id="37001001">像他那样的小人物能活着回来，天下还真是无奇不有啊……</text>
<text id="37001100">什么？那个咒术师竟然平安无事……</text>
<text id="37001101">像他那样的小人物能活着回来，天下还真是无奇不有啊……</text>
<text id="37001200">说到这边，你为什么不冶炼武器呢？</text>
<text id="37001201">如果你不知道安德烈老爹的话，
不妨从不死教堂往下走，到森林的古老教堂走一趟。</text>
<text id="37001202">如果你不知道安德烈老爹的话，
最好还是早点去找他。</text>
<text id="37001203">……但话说回来，如果你就是喜欢用钝钝的武器，那就随你高兴啦！</text>
<text id="37001204">哇哈哈哈哈哈</text>
<text id="37001300">说到这边，你应该也见过了吧？</text>
<text id="37001301">……那#1系火女#3#2防火女#3呀。</text>
<text id="37001302">她的职责似乎就是一直待在那边，
避免不死营火熄灭。</text>
<text id="37001303">唉，真是够惨的了。话也没办法说，哪儿都去不了。</text>
<text id="37001304">我猜那女的，她故乡的人一定是拔了她的舌头，
让她喊不出神的名字。</text>
<text id="37001305">所谓的虔诚善人，还真是了不起呀。
我绝对办不到的，真是佩服！</text>
<text id="37001306">哇哈哈哈哈哈</text>
<text id="37001400">……你那张脸简直就和游魂没两样嘛。</text>
<text id="37001401">大概是因为死得太过头了，不过照这样下去，
可是马上就会变成真的游魂喔。得要赶紧取得人性呀。</text>
<text id="37001402">……不过话说回来，说不定成为游魂反而比较轻松呢。</text>
<text id="37001403">……呵呵呵呵呵</text>
<text id="37001500">喔？怎么啦？怎样收集人性？</text>
<text id="37001501">虽说要怎么做还是看你的决定啦……</text>
<text id="37001502">##看是要踏实地捡尸体收集……</text>
<text id="37001503">看是要踏实地捡尸体收集……
或是和那票圣职一样，狼狈为奸地相互召唤彼此……</text>
<text id="37001504">另外，虽然我自己是办不到啦，
不过最快的方法，就是杀害正常的不死人来夺取人性。</text>
<text id="37001505">杀人来夺取，说不定反而是最贴近人性的做法呢……</text>
<text id="37001506">……呵呵呵呵呵</text>
<text id="37001600">……虽然这样讲，但你可别对我下手呀。</text>
<text id="37001601">把事情想得太简单，日后可是会后悔的……</text>
<text id="37001700">喂！难不成……你遭到诅咒了？</text>
<text id="37001701">这还真是不死人中的不死人啊，
节哀顺变啦。</text>
<text id="37001702">哇哈哈哈哈哈</text>
<text id="37001703">哇哈哈哈哈哈</text>
<text id="37001704">啊，抱歉、抱歉。就让我教你一件事来致歉吧。</text>
<text id="37001705">虽然那是很久前的事了……
但我曾听说小隆德有一位解咒师。</text>
<text id="37001706">反正就算没找到也不过是和现在一样而已，去走一遭也没差吧？</text>
<text id="37001707">不过，即便是真的没找到也别怨我呀！</text>
<text id="37001708">哇哈哈哈哈哈</text>
<text id="37001709">喂，你看到了吗？</text>
<text id="37001800">那真的是“大帽子”啊，传说中的魔法师耶。</text>
<text id="37001801">……真是的，这边究竟怎么了？
英雄一箩筐。</text>
<text id="37001802">看来我真不该再待着，感觉真差……</text>
<text id="37001803">……呵呵呵呵呵</text>
<text id="37001900">……你应该看到了吧？</text>
<text id="37001901">听说似乎是高贵的圣女一行人来了。</text>
<text id="37001902">不过就是去墓地搞破坏，大小姐、大小姐地叫，
一群娇生惯养的小鬼，听了我都想吐。</text>
<text id="37001903">我想你应该也有同感吧？</text>
<text id="37001904">啧……</text>
<text id="37002000">……你知道吗？</text>
<text id="37002001">后来那个高贵的圣女自己回到了这边……
整身衣衫破破烂烂的。</text>
<text id="37002002">不知是随侍死了，还是抛下她……不管怎样，看了真是痛快啊。</text>
<text id="37002003">贵族有什么了不起啊。</text>
<text id="37002004">哇哈哈哈哈哈</text>
<text id="37002100">圣女？</text>
<text id="37002101">不知道已经去哪了呢。会不会是到不死教堂那里了？</text>
<text id="37002102">也是啦，对于高贵的人来说，应该是不会喜欢这种遗迹吧？</text>
<text id="37002200">你已经敲响了第二口钟了吧？</text>
<text id="37002201">哎呀，实在太猛了，真令我吃惊……不过却出现了个奇怪家伙。</text>
<text id="37002202">不仅声音和鼾声都超级大声，嘴巴也是臭到不行……</text>
<text id="37002203">真是让人笑不出来啊……</text>
<text id="37002300">可恶，把这边也都搞臭了……这边原本是个很舒服的地方呢。</text>
<text id="37002301">唉……</text>
<text id="37002302">我要不要也试着再多努力些呢……</text>
<text id="37002400">怎么啦？是你呀。</text>
<text id="37002401">虽然没什么特别要说的事……</text>
<text id="37002402">但话说回来，先前倒也发生一件怪事。</text>
<text id="37002403">呃，就是那只乌鸦啊，
抓着一个蜷曲起来的人不知飞到哪去了。</text>
<text id="37002404">那究竟是怎么一回事呢……</text>
<text id="37002405">真是搞不懂呀……</text>
<text id="37002500">嗯？怎么了吗？</text>
<text id="37002501">我和你完全无话可说啦，别烦我了。</text>
<text id="37002600">那，你想怎么做啊？</text>
<text id="37002601">像我就是这样啦。</text>
<text id="37002602">虽然丢脸，但毕竟我已经灰心丧志了……</text>
<text id="37002700">哇！</text>
<text id="37002710">好痛！</text>
<text id="37002720">你在搞什么鬼！</text>
<text id="37002730">喂！住手！</text>
<text id="37002800">混账！胆子不小！</text>
<text id="37002801">虽说我已灰心丧志，但也别小看我！你这浑小子！</text>
<text id="37002802">我绝对会让你后悔莫及！</text>
<text id="37002900">嘿嘿，干得好……</text>
<text id="37002901">终于可以结束了……</text>
<text id="37003000">混账东西……</text>
<text id="37003001">你就这样被我解决，还有戏唱吗……</text>
<text id="37003100">说到这边，你为什么不冶炼武器？</text>
<text id="37003101">如果还没有拿到打铁箱的话，最好还是早点去找。</text>
<text id="37003102">……但话说回来，如果你就是喜欢用钝钝的武器，那就随你高兴啦！</text>
<text id="37003103">哇哈哈哈哈哈</text>
<text id="37003104">……你为什么都不修理武器？</text>
<text id="37003105">修理用的粉和工具什么的不是都一应俱全吗？</text>
<text id="37003106">……只有那些脑筋不知在想什么的英雄，
才会喜欢用已经坏了的武器吧。</text>
<text id="37003107">哇哈哈哈哈哈</text>
</entries>