<?xml version="1.0" encoding="utf-8"?>
<entries>
<text id="100">哈维尔戒指</text>
<text id="101">红泪石戒指</text>
<text id="102">暗月之剑誓约戒指</text>
<text id="103">猫誓约戒指</text>
<text id="104">绿花戒指</text>
<text id="105">火方石戒指</text>
<text id="106">雷方石戒指</text>
<text id="107">法术方石戒指</text>
<text id="108">斑方石戒指</text>
<text id="109">咬血戒指</text>
<text id="110">咬毒戒指</text>
<text id="111">微小生命戒指</text>
<text id="113">咬咒戒指</text>
<text id="114">白教司祭戒指</text>
<text id="115">狂吼龙徽戒指</text>
<text id="116">幽暗宝冠戒指</text>
<text id="117">黄蜂戒指</text>
<text id="119">老鹰戒指</text>
<text id="120">钢铁庇佑戒指</text>
<text id="121">贪婪金蛇戒指</text>
<text id="122">贪婪银蛇戒指</text>
<text id="123">沉眠龙徽戒指</text>
<text id="124">浓雾戒指</text>
<text id="125">生锈铁环</text>
<text id="126">牺牲戒指</text>
<text id="127">宝贵牺牲戒指</text>
<text id="128">暗沉木纹戒指</text>
<text id="130">太阳公主戒指</text>
<text id="137">老魔女戒指</text>
<text id="138">亚尔特留斯的契约</text>
<text id="139">焦黑橘色戒指</text>
<text id="141">伫立龙徽戒指</text>
<text id="142">邪眼戒指</text>
<text id="143">宠爱庇佑戒指</text>
<text id="144">狮子戒指</text>
<text id="145">东方木纹戒指</text>
<text id="146">狼戒指</text>
<text id="147">蓝泪石戒指</text>
<text id="148">太阳长男戒指</text>
<text id="149">暗月司祭戒指</text>
<text id="150">灾难戒指</text>
<text id="133">##谴责之戒</text>
<text id="134">##蒙蔽幽灵戒指</text>
<text id="140">##替身戒指</text>
</entries>