<?xml version="1.0" encoding="utf-8"?>
<entries>
<text id="75300000">Undead! Undead!</text>
<text id="75300010">Keep your hands off our bell, the great Bell of Alken!</text>
<text id="75310010">Keep your hands off our bell, the great Bell of Venn!</text>
<text id="75300020">The bell belongs! To the Princess, it do!</text>
<text id="75310020">The bell belongs! To the Prince, it do!</text>
<text id="75300030">Stay back, or we slice! Slice you to bits!
Me and my chums, we shan't be miffed!</text>
<text id="75300040">Stay back, or you're pieces! Tiniest pieces! Hah hah hah hah!</text>
<text id="75300100">A long, long, long time ago, the Princess,
she made me, yes, just like so!</text>
<text id="75310100">A long, long, long time ago, the Prince,
he made me, yes, just like so!</text>
<text id="75300110">To guard this bell! For the prince's honour!</text>
<text id="75310110">To guard this bell! Princess's honour!</text>
<text id="75300120">Stay away, foul Undead, or you'll be a goner! Hah hah hah hah!</text>
<text id="75300130">Stay back! It belongs, to the Princess, it do!</text>
<text id="75310130">Stay back! It belongs to the Prince, yes it do!</text>
<text id="75300140">Mwah hah hah, ooh hoo hoo!</text>
<text id="75300200">Hah hah hah, ooh hoo hoo!</text>
<text id="75300210">You wish to guard the bell, you do?</text>
<text id="75300220">For the Prince, and the Princess,
forever, for true?</text>
<text id="75310220">For the Princess, and Prince?
Forever, for true?</text>
<text id="75300300">Hah hah, heh! Here, for you!</text>
<text id="75300310">When you're 'round the bell, you'll be brought near!</text>
<text id="75300320">When the bell is in trouble, the ring brings you here!</text>
<text id="75300330">Slice 'em to shreds, whoever they are! 
Wherever, whoever, be they near, be they far!</text>
<text id="75300340">Slice 'em to pieces! For the Princess!</text>
<text id="75310340">Slice 'em to pieces! For the Prince, yes!</text>
<text id="75300350">Hah hah hah! Oh, ah, hoo...</text>
<text id="75300360">Bwah hah hah hah!</text>
<text id="75300400">Gah hah hah hah hah!</text>
<text id="75300410">Useless fool! Filthy Undead!</text>
<text id="75300420">Be gone, right now, or it's off with your head! Ah hah hah hah!</text>
<text id="75300500">You want to guard the bell, do you?</text>
<text id="75300510">For the Prince and the Princess,
forever, for true?</text>
<text id="75310510">For the Princess, and Prince,
forever, for true?</text>
<text id="75300600">Ah hah hah! The Princess made me!
To guard the Bell of Alken!</text>
<text id="75310600">The Prince made me!
To guard the Bell of Venn!</text>
<text id="75300610">In Alken! The bell! Of the princess! 
In Venn! The bell! Of the prince, yes!</text>
<text id="75310610">In Venn! The bell! Of the fine prince!
In Alken! The bell! Of the princess!</text>
<text id="75300620">Tear 'em to shreds, tear 'em to bits!
Gather around, and ring the bell swift!</text>
<text id="75300630">We've been ringing this bell forever, we have!
Ah hah hah hah!</text>
<text id="75300700">Gah hah! Hah hah hah!</text>
<text id="75300710">That's it! Bravo! Tear 'em to shreds!</text>
<text id="75300720">Slice 'em and dice 'em, and bring me their heads! Ah hah hah!</text>
<text id="75300800">Bravo, my friend, look how they've bled!</text>
<text id="75300810">Keep slicin'! And dicin'! Till they're all little shreds, heh!</text>
<text id="75300820">Hah hah, ooh hoo!</text>
<text id="75300900">Hah! Haaaah!</text>
<text id="75300910">You are the best! The absolute best!</text>
<text id="75300920">Heh, hah hah hah!</text>
<text id="75305000">Bah! I'll slice you to shreds!</text>
<text id="75305010">The Undead is back! That silly Undead!</text>
<text id="75305020">Aggh hah hah hah hah, dee hee, hee...</text>
<text id="75305030">Agh hoo hoo, hah hah hah!</text>
<text id="75305040">Ooh hoo hoo, ah hah hah!</text>
<text id="75305050">Hah hah hah, gah hah hah, ooh...</text>
<text id="75305060">Slice you to pieces, miniature pieces...arrgh!</text>
<text id="75305070">Yarghh hee hee hee hee!</text>
<text id="75306000">##Forever...for true!</text>
<text id="75307000">Hah hah hah, ooh hoo, ohh...</text>
<text id="75307010">Take these! Take 'em! Take 'em for you!</text>
<text id="75307020">Hmmgg.... Mwah hah hah hah!</text>
</entries>